README.rst
setup.py
dss/Mixin.py
dss/Serializer.py
dss/TimeFormatFactory.py
dss/Warning.py
dss/__init__.py
dss_serializer.egg-info/PKG-INFO
dss_serializer.egg-info/SOURCES.txt
dss_serializer.egg-info/dependency_links.txt
dss_serializer.egg-info/requires.txt
dss_serializer.egg-info/top_level.txt
dss_serializer.egg-info/zip-safe
test/test_Mixin.py
test/test_Serializer.py
test/test_TimeFormatFactory.py