Metadata-Version: 1.1
Name: dss-serializer
Version: 1.1
Summary: Django Simple Serializer is a serializer to help user serialize django data or python list into json,xml,dict data in a simple way.
Home-page: https://github.com/hengdai/django-simple-serializer
Author: RaPoSpectre
Author-email: rapospectre@gmail.com
License: MIT
Keywords: django serializer
Platform: UNKNOWN
Classifier: License :: OSI Approved :: MIT License
Classifier: Programming Language :: Python
Classifier: Intended Audience :: Developers
Classifier: Operating System :: OS Independent
